xq_pulse/__init__.py
xq_pulse/pulse/__init__.py
xq_pulse/pulse/channel.py
xq_pulse/pulse/channel_mapping.py
xq_pulse/pulse/dsl.py
xq_pulse/pulse/envelope.py
xq_pulse/pulse/expression.py
xq_pulse/pulse/program.py
xq_pulse/pulse/pulse.py
xq_pulse/pulse/serialization.py
xq_pulse/pulse/setup.py
xq_pulse/pulse/validators.py
xq_pulse/util/__init__.py
xq_pulse/util/units.py
xq_pulse-0.2.0.dist-info/WHEEL
xq_pulse-0.2.0.dist-info/METADATA
xq_pulse-0.2.0.dist-info/RECORD
