Metadata-Version: 2.3
Name: xq-pulse
Version: 0.2.0
Summary: Pulse program implementation library
Author: Pit Hüne
Author-email: Pit Hüne <pit@xeedq.com>
Requires-Dist: attrs>=25.3.0
Requires-Dist: cattrs>=24.1.0
Requires-Dist: frozendict>=2.4.6
Requires-Dist: intervaltree>=3.1.0
Requires-Dist: pint>=0.24.4
Requires-Dist: plotly>=5.24.1
Requires-Dist: plotly-resampler>=0.11.0
Requires-Dist: python-constraint2>=2.4.0
Requires-Python: >=3.10
